planqk/commons/__init__.py
planqk/commons/_version.py
planqk/commons/constants.py
planqk/commons/datapool.py
planqk/commons/entrypoint.py
planqk/commons/file.py
planqk/commons/json.py
planqk/commons/logging.py
planqk/commons/parameters.py
planqk/commons/reflection.py
planqk/commons/secret.py
planqk/commons/string.py
planqk/commons/openapi/__init__.py
planqk/commons/openapi/file.py
planqk/commons/openapi/generator.py
planqk/commons/openapi/schema.py
planqk/commons/openapi/template-managed-service.yaml
planqk/commons/openapi/template.py
planqk/commons/runtime/__init__.py
planqk/commons/runtime/input.py
planqk/commons/runtime/main.py
planqk/commons/runtime/output.py
planqk_commons-1.31.2.dist-info/licenses/LICENSE
planqk_commons-1.31.2.dist-info/METADATA
planqk_commons-1.31.2.dist-info/WHEEL
planqk_commons-1.31.2.dist-info/top_level.txt
planqk_commons-1.31.2.dist-info/RECORD
