Metadata-Version: 2.4
Name: planqk-commons
Version: 1.31.2
Summary: Set of common utilities and classes to boost development of quantum computing applications using PLANQK.
Author-email: Kipu Quantum GmbH <info@kipu-quantum.com>
Maintainer-email: Michael Wurster <michael.wurster@kipu-quantum.com>, Lukas Harzenetter <lukas.harzenetter@kipu-quantum.com>, Sebastian Wagner <sebastian.wagner@kipu-quantum.com>
License:                                  Apache License
Project-URL: Homepage, https://kipu-quantum.com/platform
Project-URL: Documentation, https://docs.planqk.de
Project-URL: Repository, https://gitlab.com/planqk-foss/planqk-commons
Project-URL: Issues, https://gitlab.com/planqk-foss/planqk-commons/-/issues
Project-URL: Changelog, https://gitlab.com/planqk-foss/planqk-commons/-/releases
Classifier: Programming Language :: Python :: 3
Classifier: License :: OSI Approved :: Apache Software License
Classifier: Operating System :: OS Independent
Requires-Python: >=3.10
License-File: LICENSE
Requires-Dist: loguru>=0.7.3
Requires-Dist: pydantic<2.10,>=2.5.0
Requires-Dist: pyyaml>=6.0.2
Dynamic: license-file
